Workbook

Sheet Executive Summary
B2: CAPSTONE EXECUTIVE SUMMARY
B3: High-level aggregated leadership report connected to Transaction Master.
B5: Company Metric | C5: Value | D5: Benchmark Target | E5: Status
B6: Total Sales Revenue ($) | C6: ='Transaction Master'!H14 | D6: 50000 | E6: =IF(C6>=D6,"Target Exceeded","Needs Attention")
B7: Total Cost of Goods ($) | C7: ='Transaction Master'!I14 | D7: 25000 | E7: =IF(C7<=D7,"Cost Controlled","Over Budget")
B8: Net Operating Margin ($) | C8: ='Transaction Master'!J14 | D8: 25000 | E8: =IF(C8>=D8,"Target Exceeded","Needs Attention")
B9: Blended Gross Margin % | C9: =C8/C6 | D9: 0.5 | E9: =IF(C9>=D9,"Healthy Margin","Compressed Margin")
B10: Total Units Sold (#) | C10: ='Transaction Master'!E14 | D10: 150 | E10: =IF(C10>=D10,"Volume Met","Volume Short")

Sheet Transaction Master
B2: DAY 14 CAPSTONE PROJECT: ENTERPRISE FINANCIAL MODEL
B3: Comprehensive pipeline combining Lookups, Formulas, Margin analysis, and KPI Summaries.
B5: OrderID | C5: Customer | D5: Item SKU | E5: Units | F5: Unit List Price ($) | G5: Discount Applied | H5: Final Revenue ($) | I5: COGS ($) | J5: Net Margin ($)
B6: ORD-901 | C6: Acme Corp | D6: SKU-PRO-01 | E6: 15 | F6: =VLOOKUP(D6,'Product Catalog'!$B$6:$D$10,2,FALSE) | G6: 0.1 | H6: =E6*F6*(1-G6) | I6: =E6*VLOOKUP(D6,'Product Catalog'!$B$6:$D$10,3,FALSE) | J6: =H6-I6
B7: ORD-902 | C7: Globex LLC | D7: SKU-PRO-03 | E7: 24 | F7: =VLOOKUP(D7,'Product Catalog'!$B$6:$D$10,2,FALSE) | G7: 0.15 | H7: =E7*F7*(1-G7) | I7: =E7*VLOOKUP(D7,'Product Catalog'!$B$6:$D$10,3,FALSE) | J7: =H7-I7
B8: ORD-903 | C8: Soylent Inc | D8: SKU-PRO-02 | E8: 8 | F8: =VLOOKUP(D8,'Product Catalog'!$B$6:$D$10,2,FALSE) | G8: 0.05 | H8: =E8*F8*(1-G8) | I8: =E8*VLOOKUP(D8,'Product Catalog'!$B$6:$D$10,3,FALSE) | J8: =H8-I8
B9: ORD-904 | C9: Initech LLC | D9: SKU-PRO-05 | E9: 30 | F9: =VLOOKUP(D9,'Product Catalog'!$B$6:$D$10,2,FALSE) | G9: 0.2 | H9: =E9*F9*(1-G9) | I9: =E9*VLOOKUP(D9,'Product Catalog'!$B$6:$D$10,3,FALSE) | J9: =H9-I9
B10: ORD-905 | C10: Umbrella Corp | D10: SKU-PRO-04 | E10: 12 | F10: =VLOOKUP(D10,'Product Catalog'!$B$6:$D$10,2,FALSE) | G10: 0 | H10: =E10*F10*(1-G10) | I10: =E10*VLOOKUP(D10,'Product Catalog'!$B$6:$D$10,3,FALSE) | J10: =H10-I10
B11: ORD-906 | C11: Acme Corp | D11: SKU-PRO-02 | E11: 18 | F11: =VLOOKUP(D11,'Product Catalog'!$B$6:$D$10,2,FALSE) | G11: 0.1 | H11: =E11*F11*(1-G11) | I11: =E11*VLOOKUP(D11,'Product Catalog'!$B$6:$D$10,3,FALSE) | J11: =H11-I11
B12: ORD-907 | C12: Massive Dynamic | D12: SKU-PRO-01 | E12: 22 | F12: =VLOOKUP(D12,'Product Catalog'!$B$6:$D$10,2,FALSE) | G12: 0.12 | H12: =E12*F12*(1-G12) | I12: =E12*VLOOKUP(D12,'Product Catalog'!$B$6:$D$10,3,FALSE) | J12: =H12-I12
B13: ORD-908 | C13: Stark Industries | D13: SKU-PRO-05 | E13: 45 | F13: =VLOOKUP(D13,'Product Catalog'!$B$6:$D$10,2,FALSE) | G13: 0.25 | H13: =E13*F13*(1-G13) | I13: =E13*VLOOKUP(D13,'Product Catalog'!$B$6:$D$10,3,FALSE) | J13: =H13-I13
B14: Portfolio Total | E14: =SUM(E6:E13) | H14: =SUM(H6:H13) | I14: =SUM(I6:I13) | J14: =SUM(J6:J13)

Sheet Product Catalog
B2: PRODUCT MASTER CATALOG
B3: Reference table for pricing, unit costs, and baseline markup.
B5: SKU Code | C5: Item Name | D5: Unit List Price ($) | E5: Unit Cost ($) | F5: Target Margin %
B6: SKU-PRO-01 | C6: Enterprise Cloud Gateway | D6: 250 | E6: 110 | F6: =(C6-D6)/C6
B7: SKU-PRO-02 | C7: Hardware Security Module | D7: 480 | E7: 220 | F7: =(C7-D7)/C7
B8: SKU-PRO-03 | C8: Managed Analytics Agent | D8: 150 | E8: 45 | F8: =(C8-D8)/C8
B9: SKU-PRO-04 | C9: AI Inference Appliance | D9: 890 | E9: 490 | F9: =(C9-D9)/C9
B10: SKU-PRO-05 | C10: Network Monitoring Probe | D10: 95 | E10: 32 | F10: =(C10-D10)/C10
